dcat/__init__.py
dcat/admin.py
dcat/apps.py
dcat/models.py
dcat/tests.py
dcat/views.py
dcat/management/__init__.py
dcat/management/commands/__init__.py
dcat/management/commands/dump_from_datajson.py
dcat/management/commands/import_filetypes.py
dcat/management/commands/import_from_datajson.py
dcat/management/commands/import_licences.py
dcat/migrations/0001_initial.py
dcat/migrations/0002_alter_agent_type_alter_distribution_file_and_more.py
dcat/migrations/0003_checksum_distribution_checksum.py
dcat/migrations/0004_alter_distribution_checksum.py
dcat/migrations/__init__.py
django_dcat-0.1.2.dist-info/LICENSE
django_dcat-0.1.2.dist-info/METADATA
django_dcat-0.1.2.dist-info/WHEEL
django_dcat-0.1.2.dist-info/top_level.txt
django_dcat-0.1.2.dist-info/RECORD
